healthcheck_cli/__init__.py
healthcheck_cli/main.py
healthcheck_cli/commands/__init__.py
healthcheck_cli/commands/health.py
healthcheck_cli/utils/__init__.py
healthcheck_cli/utils/healthchecker.py
healthcheck_cli-1.0.0.dist-info/licenses/LICENSE
healthcheck_cli-1.0.0.dist-info/METADATA
healthcheck_cli-1.0.0.dist-info/WHEEL
healthcheck_cli-1.0.0.dist-info/entry_points.txt
healthcheck_cli-1.0.0.dist-info/top_level.txt
healthcheck_cli-1.0.0.dist-info/RECORD
